tico/__init__.py
tico/pt2_to_circle.py
tico/config/__init__.py
tico/config/base.py
tico/config/factory.py
tico/config/v1.py
tico/experimental/__init__.py
tico/experimental/quantization/__init__.py
tico/experimental/quantization/config.py
tico/experimental/quantization/public_interface.py
tico/experimental/quantization/quantizer.py
tico/experimental/quantization/algorithm/__init__.py
tico/experimental/quantization/algorithm/gptq/__init__.py
tico/experimental/quantization/algorithm/gptq/gptq.py
tico/experimental/quantization/algorithm/gptq/quant.py
tico/experimental/quantization/algorithm/gptq/quantizer.py
tico/experimental/quantization/algorithm/gptq/utils.py
tico/experimental/quantization/algorithm/pt2e/__init__.py
tico/experimental/quantization/algorithm/pt2e/quantizer.py
tico/experimental/quantization/algorithm/pt2e/utils.py
tico/experimental/quantization/algorithm/pt2e/annotation/__init__.py
tico/experimental/quantization/algorithm/pt2e/annotation/annotator.py
tico/experimental/quantization/algorithm/pt2e/annotation/config.py
tico/experimental/quantization/algorithm/pt2e/annotation/spec.py
tico/experimental/quantization/algorithm/pt2e/annotation/utils.py
tico/experimental/quantization/algorithm/pt2e/annotation/op/__init__.py
tico/experimental/quantization/algorithm/pt2e/annotation/op/adaptive_avg_pool2d.py
tico/experimental/quantization/algorithm/pt2e/annotation/op/add.py
tico/experimental/quantization/algorithm/pt2e/annotation/op/conv2d.py
tico/experimental/quantization/algorithm/pt2e/annotation/op/div.py
tico/experimental/quantization/algorithm/pt2e/annotation/op/linear.py
tico/experimental/quantization/algorithm/pt2e/annotation/op/mean.py
tico/experimental/quantization/algorithm/pt2e/annotation/op/mul.py
tico/experimental/quantization/algorithm/pt2e/annotation/op/relu6.py
tico/experimental/quantization/algorithm/pt2e/annotation/op/rsqrt.py
tico/experimental/quantization/algorithm/pt2e/annotation/op/sub.py
tico-0.1.0.dist-info/LICENSE
tico-0.1.0.dist-info/METADATA
tico-0.1.0.dist-info/WHEEL
tico-0.1.0.dist-info/entry_points.txt
tico-0.1.0.dist-info/top_level.txt
tico-0.1.0.dist-info/RECORD
